wnaget/__init__.py
wnaget/wnaget.py
wnaget-0.1.dist-info/METADATA
wnaget-0.1.dist-info/WHEEL
wnaget-0.1.dist-info/entry_points.txt
wnaget-0.1.dist-info/top_level.txt
wnaget-0.1.dist-info/RECORD
